ai/__init__.py
ai/starlake/__init__.py
ai/starlake/helper/__init__.py
ai/starlake/snowflake/__init__.py
ai/starlake/snowflake/exceptions.py
ai/starlake/snowflake/starlake_snowflake_job.py
ai/starlake/snowflake/starlake_snowflake_orchestration.py
starlake_snowflake-0.3.4.dist-info/licenses/LICENSE
starlake_snowflake-0.3.4.dist-info/METADATA
starlake_snowflake-0.3.4.dist-info/WHEEL
starlake_snowflake-0.3.4.dist-info/top_level.txt
starlake_snowflake-0.3.4.dist-info/RECORD
