Metadata-Version: 2.4
Name: starlake-snowflake
Version: 0.3.4
Summary: Starlake Python Distribution For Snowflake
Author: Stéphane Manciot
Author-email: stephane.manciot@gmail.com
License: Apache 2.0
License-File: LICENSE
Requires-Dist: starlake-orchestration~=0.4
Requires-Dist: croniter
Requires-Dist: sqlalchemy
Requires-Dist: snowflake
Requires-Dist: snowflake.core
Requires-Dist: snowflake-snowpark-python
Provides-Extra: snwoflake
Provides-Extra: shell
Provides-Extra: gcp
Provides-Extra: aws
Provides-Extra: azure
Dynamic: author
Dynamic: author-email
Dynamic: description-content-type
Dynamic: license
Dynamic: license-file
Dynamic: provides-extra
Dynamic: requires-dist
Dynamic: summary
